sigdigs/__init__.py
esoteric_sigdigs-0.1.5.dist-info/LICENSE
esoteric_sigdigs-0.1.5.dist-info/METADATA
esoteric_sigdigs-0.1.5.dist-info/WHEEL
esoteric_sigdigs-0.1.5.dist-info/top_level.txt
esoteric_sigdigs-0.1.5.dist-info/RECORD
