Metadata-Version: 2.1
Name: esoteric-sigdigs
Version: 0.1.5
Summary: A Python package that detects and rounds numbers to significant digits.
Home-page: https://github.com/ericli3690/esoteric-sigdigs/
Author: Eric Li
Author-email: ericli3690@gmail.com
Classifier: Programming Language :: Python :: 3
Classifier: License :: OSI Approved :: MIT License
Classifier: Operating System :: OS Independent
Requires-Python: >=3.8.0
License-File: LICENSE
